krx_hj3415/__init__.py
krx_hj3415/cli.py
krx_hj3415/domain/__init__.py
krx_hj3415/domain/diff.py
krx_hj3415/domain/types.py
krx_hj3415/domain/universe.py
krx_hj3415/provider/__init__.py
krx_hj3415/provider/krx300_samsungfund_excel.py
krx_hj3415/usecases/__init__.py
krx_hj3415/usecases/sync_universe.py
krx_hj3415-2.2.3.dist-info/entry_points.txt
krx_hj3415-2.2.3.dist-info/licenses/LICENSE
krx_hj3415-2.2.3.dist-info/WHEEL
krx_hj3415-2.2.3.dist-info/METADATA
krx_hj3415-2.2.3.dist-info/RECORD
