Metadata-Version: 2.4
Name: krx-hj3415
Version: 2.2.3
Summary: KRX300 code scraper
Keywords: example,demo
Author-email: Hyungjin Kim <hj3415@gmail.com>
Requires-Python: >=3.11
Classifier: Programming Language :: Python :: 3
Classifier: License :: OSI Approved :: MIT License
Classifier: Typing :: Typed
License-File: LICENSE
Requires-Dist: requests>=2.32.5
Requires-Dist: pandas>=2.3.3
Requires-Dist: openpyxl>=3.1.5
Requires-Dist: xlrd>=2.0.2
Requires-Dist: typer>=0.21.1
Requires-Dist: db2-hj3415
Requires-Dist: contracts-hj3415
Requires-Dist: domain-hj3415
